abletonparsing/__init__.py
abletonparsing/abletonparsing.py
abletonparsing-0.1.3.dist-info/licenses/LICENSE
abletonparsing-0.1.3.dist-info/METADATA
abletonparsing-0.1.3.dist-info/WHEEL
abletonparsing-0.1.3.dist-info/top_level.txt
abletonparsing-0.1.3.dist-info/RECORD
