Metadata-Version: 2.4
Name: abletonparsing
Version: 0.1.3
Summary: Python module for parsing Ableton Live ASD clip files containing warp markers.
Home-page: https://github.com/DBraun/AbletonParsing
Author: David Braun
Author-email: braun@ccrma.stanford.edu
Project-URL: Bug Tracker, https://github.com/DBraun/AbletonParsing/issues
Classifier: Programming Language :: Python :: 3
Classifier: License :: OSI Approved :: MIT License
Classifier: Operating System :: OS Independent
Requires-Python: >=3.8
License-File: LICENSE
Provides-Extra: test
Requires-Dist: pytest; extra == "test"
Requires-Dist: librosa; extra == "test"
Requires-Dist: soundfile; extra == "test"
Requires-Dist: pyrubberband; extra == "test"
Dynamic: license-file
